{
  "_class": "shapePath",
  "booleanOperation": 0,
  "do_objectID": "6FEBD9B2-A996-4BC6-A4FE-B134C714C122",
  "edited": true,
  "exportOptions": {
    "_class": "exportOptions",
    "exportFormats": [
    ],
    "includedLayerIds": [
    ],
    "layerOptions": 0,
    "shouldTrim": false
  },
  "frame": {
    "_class": "rect",
    "constrainProportions": false,
    "height": 7,
    "width": 11,
    "x": 30,
    "y": 36
  },
  "isClosed": true,
  "isFlippedHorizontal": false,
  "isFlippedVertical": false,
  "isLocked": false,
  "isVisible": true,
  "layerListExpandedType": 0,
  "name": "Shape",
  "nameIsFixed": false,
  "path": {
    "_class": "path",
    "isClosed": true,
    "pointRadiusBehaviour": 1,
    "points": [
      {
        "_class": "curvePoint",
        "cornerRadius": 0,
        "curveFrom": "{0.10362634739010877, 1}",
        "curveMode": 1,
        "curveTo": "{0.10362634739010877, 1}",
        "hasCurveFrom": false,
        "hasCurveTo": false,
        "point": "{0.10362634739010877, 1}"
      },
      {
        "_class": "curvePoint",
        "cornerRadius": 0,
        "curveFrom": "{0, 0.58649999999999991}",
        "curveMode": 1,
        "curveTo": "{0, 0.58649999999999991}",
        "hasCurveFrom": false,
        "hasCurveTo": false,
        "point": "{0, 0.58649999999999991}"
      },
      {
        "_class": "curvePoint",
        "cornerRadius": 0,
        "curveFrom": "{0.89637365260989121, 0}",
        "curveMode": 1,
        "curveTo": "{0.89637365260989121, 0}",
        "hasCurveFrom": false,
        "hasCurveTo": false,
        "point": "{0.89637365260989121, 0}"
      },
      {
        "_class": "curvePoint",
        "cornerRadius": 0,
        "curveFrom": "{1, 0.41350000000000009}",
        "curveMode": 1,
        "curveTo": "{1, 0.41350000000000009}",
        "hasCurveFrom": false,
        "hasCurveTo": false,
        "point": "{1, 0.41350000000000009}"
      }
    ]
  },
  "pointRadiusBehaviour": 1,
  "points": [
    {
      "_class": "curvePoint",
      "cornerRadius": 0,
      "curveFrom": "{0.10362634739010877, 1}",
      "curveMode": 1,
      "curveTo": "{0.10362634739010877, 1}",
      "hasCurveFrom": false,
      "hasCurveTo": false,
      "point": "{0.10362634739010877, 1}"
    },
    {
      "_class": "curvePoint",
      "cornerRadius": 0,
      "curveFrom": "{0, 0.58649999999999991}",
      "curveMode": 1,
      "curveTo": "{0, 0.58649999999999991}",
      "hasCurveFrom": false,
      "hasCurveTo": false,
      "point": "{0, 0.58649999999999991}"
    },
    {
      "_class": "curvePoint",
      "cornerRadius": 0,
      "curveFrom": "{0.89637365260989121, 0}",
      "curveMode": 1,
      "curveTo": "{0.89637365260989121, 0}",
      "hasCurveFrom": false,
      "hasCurveTo": false,
      "point": "{0.89637365260989121, 0}"
    },
    {
      "_class": "curvePoint",
      "cornerRadius": 0,
      "curveFrom": "{1, 0.41350000000000009}",
      "curveMode": 1,
      "curveTo": "{1, 0.41350000000000009}",
      "hasCurveFrom": false,
      "hasCurveTo": false,
      "point": "{1, 0.41350000000000009}"
    }
  ],
  "resizingConstraint": 63,
  "resizingType": 0,
  "rotation": 0,
  "shouldBreakMaskChain": false
}